MANIFEST.in
README.md
setup.py
bse_ml/.DS_Store
bse_ml/__init__.py
bse_ml/acmdenseunet.py
bse_ml/actions.py
bse_ml/ccv.py
bse_ml/create_h5.py
bse_ml/data_reader.py
bse_ml/img_utils.py
bse_ml/input_fn.m
bse_ml/main.py
bse_ml/ops.py
bse_ml/save_pred.m
bse_ml/saveastiff.m
bse_ml/test.py
bse_ml.egg-info/PKG-INFO
bse_ml.egg-info/SOURCES.txt
bse_ml.egg-info/dependency_links.txt
bse_ml.egg-info/entry_points.txt
bse_ml.egg-info/not-zip-safe
bse_ml.egg-info/requires.txt
bse_ml.egg-info/top_level.txt
bse_ml/NIfTI/FAQ.pdf
bse_ml/NIfTI/NIfTI_tools.pdf
bse_ml/NIfTI/UseANALYZE.pdf
bse_ml/NIfTI/affine.m
bse_ml/NIfTI/bipolar.m
bse_ml/NIfTI/bresenham_line3d.m
bse_ml/NIfTI/clip_nii.m
bse_ml/NIfTI/collapse_nii_scan.m
bse_ml/NIfTI/examples.txt
bse_ml/NIfTI/expand_nii_scan.m
bse_ml/NIfTI/extra_nii_hdr.m
bse_ml/NIfTI/flip_lr.m
bse_ml/NIfTI/get_nii_frame.m
bse_ml/NIfTI/license.txt
bse_ml/NIfTI/load_nii.m
bse_ml/NIfTI/load_nii_ext.m
bse_ml/NIfTI/load_nii_hdr.m
bse_ml/NIfTI/load_nii_img.m
bse_ml/NIfTI/load_untouch0_nii_hdr.m
bse_ml/NIfTI/load_untouch_header_only.m
bse_ml/NIfTI/load_untouch_nii.m
bse_ml/NIfTI/load_untouch_nii_hdr.m
bse_ml/NIfTI/load_untouch_nii_img.m
bse_ml/NIfTI/make_ana.m
bse_ml/NIfTI/make_nii.m
bse_ml/NIfTI/mat_into_hdr.m
bse_ml/NIfTI/pad_nii.m
bse_ml/NIfTI/reslice_nii.m
bse_ml/NIfTI/rri_file_menu.m
bse_ml/NIfTI/rri_orient.m
bse_ml/NIfTI/rri_orient_ui.m
bse_ml/NIfTI/rri_select_file.m
bse_ml/NIfTI/rri_xhair.m
bse_ml/NIfTI/rri_zoom_menu.m
bse_ml/NIfTI/save_nii.m
bse_ml/NIfTI/save_nii_ext.m
bse_ml/NIfTI/save_nii_hdr.m
bse_ml/NIfTI/save_untouch0_nii_hdr.m
bse_ml/NIfTI/save_untouch_header_only.m
bse_ml/NIfTI/save_untouch_nii.m
bse_ml/NIfTI/save_untouch_nii_hdr.m
bse_ml/NIfTI/save_untouch_slice.m
bse_ml/NIfTI/unxform_nii.m
bse_ml/NIfTI/verify_nii_ext.m
bse_ml/NIfTI/view_nii.m
bse_ml/NIfTI/view_nii_menu.m
bse_ml/NIfTI/xform_nii.m
bse_ml/__pycache__/acmdenseunet.cpython-37.pyc
bse_ml/__pycache__/actions.cpython-37.pyc
bse_ml/__pycache__/ccv.cpython-37.pyc
bse_ml/__pycache__/data_reader.cpython-37.pyc
bse_ml/__pycache__/img_utils.cpython-37.pyc
bse_ml/__pycache__/ops.cpython-37.pyc
bse_ml/modeldir/.DS_Store
bse_ml/modeldir/README.md
bse_ml/modeldir/checkpoint
