Metadata-Version: 1.0
Name: bse-ml
Version: 1.2.1
Summary: bse_ml
Home-page: https://github.com/yanlong-sun/DACN_package
Author: Yanlong Sun, Anand Joshi
Author-email: yanlongs@usc.edu
License: UNKNOWN
Platform: UNKNOWN
